pybrdst/__init__.py
pybrdst/pybrdst.py
pybrdst-0.1.dist-info/DESCRIPTION.rst
pybrdst-0.1.dist-info/METADATA
pybrdst-0.1.dist-info/RECORD
pybrdst-0.1.dist-info/WHEEL
pybrdst-0.1.dist-info/metadata.json
pybrdst-0.1.dist-info/top_level.txt
