Metadata-Version: 2.0
Name: pybrdst
Version: 0.1
Summary: Brazilian daylight saving time
Home-page: https://github.com/joaocarlosmendes/pybrdst
Author: João Carlos Mendes
Author-email: joaocarlos.tmendes@gmail.com
License: MIT
Download-URL: https://github.com/joaocarlosmendes/pybrdst/releases/tag/v0.1
Keywords: DST,brazilian,daylight,saving,horário,verão,brasileiro
Platform: UNKNOWN
